{
  "version": "7",
  "dialect": "postgresql",
  "entries": [
    {
      "idx": 0,
      "version": "7",
      "when": 1781355398413,
      "tag": "0000_sturdy_chameleon",
      "breakpoints": true
    },
    {
      "idx": 1,
      "version": "7",
      "when": 1781373308480,
      "tag": "0001_faulty_leader",
      "breakpoints": true
    },
    {
      "idx": 2,
      "version": "7",
      "when": 1781452157004,
      "tag": "0002_unknown_hydra",
      "breakpoints": true
    },
    {
      "idx": 3,
      "version": "7",
      "when": 1781452768674,
      "tag": "0003_public_gressill",
      "breakpoints": true
    }
  ]
}
